Devbouncer.v
//----------------------------
//--- Code your design here --
//----------------------------
`timescale 1ns/1ps
module debounce (input clk,rst,d, output q);  
  // internal signal definition
  reg val_d1, val_d2, val_save;
  
  assign q = val_save;
  
  always @(posedge clk or posedge rst) begin
    if(rst) begin
      val_d1   <= 1'b0;
      val_d2   <= 1'b0;
      val_save <= 1'b0;
    end else begin
      val_d1 <= d;
      val_d2 <= val_d1;
      if(val_d2 == val_d1) begin
        val_save <= val_d1;
      end
    end
  end
endmodule

//-------------------------------
//--- Code your testbench here --
//-------------------------------

`timescale 1ns/1ns
module tb_top();
  reg  clk;
  reg  rst;
  reg  d;
  wire q;
  debounce d1(clk,rst,d,q);
  initial begin
    clk = 1'b0;
    forever #4 clk=!clk;
  end
  initial begin
    rst = 1'b1;
    d   = 1'b0;
    #1 rst = 1'b0;
    #3 d=1;
    #1 d=0;
    #1 d=1;
    #1 d=0;
    #1 d=1;
    #1 d=0;
    #1 d=1;
    #1 d=0;
    #2 d=1;
    #1 d=0;
    #1 d=1;
    #60 d=0;
    #2 d=1;
    #1 d=0;
    #1 d=1;
    #1 d=0;
    #1 d=1;
    #1 d=0;
    #1 d=1;
    #3 d=0;
    #100;
    $finish();
  end
  initial begin
    $dumpfile("dump.vcd");
    $dumpvars;
  end
endmodule

dump.vcd
$date
	Tue May 30 20:00:20 2023
$end
$version
	ModelSim Version 6.5b
$end
$timescale
	1ps
$end
$scope module tb_top $end
$var reg 1 ! clk $end
$var reg 1 " rst $end
$var reg 1 # d $end
$var wire 1 $ q $end
$scope module d1 $end
$var wire 1 % clk $end
$var wire 1 & rst $end
$var wire 1 ' d $end
$var wire 1 $ q $end
$var reg 1 ( val_d1 $end
$var reg 1 ) val_d2 $end
$var reg 1 * val_save $end
$upscope $end
$upscope $end
$enddefinitions $end
#0
$dumpvars
0!
1"
0#
0(
0)
0*
0$
0'
1&
0%
$end
#1000
0"
0&
#2000
1!
1%
#4000
1#
0!
1'
0%
#5000
0#
0'
#6000
1!
1#
1'
1%
1(
#7000
0#
0'
#8000
0!
1#
1'
0%
#9000
0#
0'
#10000
1!
1#
1'
1%
1)
#11000
0#
0'
#12000
0!
0%
#13000
1#
1'
#14000
1!
0#
0'
1%
0(
1*
1$
#15000
1#
1'
#16000
0!
0%
#18000
1!
1%
1(
0)
#20000
0!
0%
#22000
1!
1%
1)
#24000
0!
0%
#26000
1!
1%
#28000
0!
0%
#30000
1!
1%
#32000
0!
0%
#34000
1!
1%
#36000
0!
0%
#38000
1!
1%
#40000
0!
0%
#42000
1!
1%
#44000
0!
0%
#46000
1!
1%
#48000
0!
0%
#50000
1!
1%
#52000
0!
0%
#54000
1!
1%
#56000
0!
0%
#58000
1!
1%
#60000
0!
0%
#62000
1!
1%
#64000
0!
0%
#66000
1!
1%
#68000
0!
0%
#70000
1!
1%
#72000
0!
0%
#74000
1!
1%
#75000
0#
0'
#76000
0!
0%
#77000
1#
1'
#78000
1!
0#
0'
1%
0(
#79000
1#
1'
#80000
0!
0#
0'
0%
#81000
1#
1'
#82000
1!
0#
0'
1%
0)
#83000
1#
1'
#84000
0!
0%
#86000
0#
1!
0'
1%
0*
0$
